README.md
setup.cfg
setup.py
bin/rfcbibtex
rfc_bibtex/__init__.py
rfc_bibtex/errors.py
rfc_bibtex/exceptions.py
rfc_bibtex/parser.py
rfc_bibtex/rfc_bibtex.py
rfc_bibtex/utils.py
rfc_bibtex.egg-info/PKG-INFO
rfc_bibtex.egg-info/SOURCES.txt
rfc_bibtex.egg-info/dependency_links.txt
rfc_bibtex.egg-info/top_level.txt