Metadata-Version: 2.1
Name: rfc-bibtex
Version: 0.3.2
Summary: Generate Bibtex entries for IETF RFCs and Internet Drafts. This version of the project has been deprecated. Please use https://github.com/iluxonchik/rfc-bibtex/ instead. You can install the new version with pip install rfcbibtex
Home-page: https://github.com/iluxonchik/rfc-bibtex-deprecated/
Author: Illya Gerasymchuk
Author-email: illya@iluxonchik.me
License: MIT
Download-URL: https://github.com/iluxonchik/rfc-bibtex/archive/0.3.2.tar.gz
Keywords: rfc,internet draft,latex,bibtex,ietf
Platform: UNKNOWN
Classifier: Programming Language :: Python :: 3.6
Classifier: Programming Language :: Python :: 3.7
Classifier: Intended Audience :: Developers
Classifier: License :: OSI Approved :: MIT License
Classifier: Operating System :: OS Independent
